README.md
setup.cfg
setup.py
PaymentSDK/__init__.py
PaymentSDK/Transfermovil/APICredentials.py
PaymentSDK/Transfermovil/APIPayload.py
PaymentSDK/Transfermovil/APIPayment.py
PaymentSDK/Transfermovil/__init__.py
etecsa_payment_sdk.egg-info/PKG-INFO
etecsa_payment_sdk.egg-info/SOURCES.txt
etecsa_payment_sdk.egg-info/dependency_links.txt
etecsa_payment_sdk.egg-info/requires.txt
etecsa_payment_sdk.egg-info/top_level.txt