Metadata-Version: 1.1
Name: etecsa-payment-sdk
Version: 1.5
Summary: Etecsa Payment SDK 
Home-page: https://github.com/sebastiancuba/etecsa-payment-sdk
Author: sebastian
Author-email: sebastian.rodriguez@etecsa.cu
License: MIT
Download-URL: https://github.com/sebastiancuba/etecsa-payment-sdk/archive/v1.0.tar.gz
Keywords: sdk
Platform: UNKNOWN
Classifier: Programming Language :: Python :: 3.8
